{
  "main": {
    "id": "f09844ea28fc4784",
    "type": "split",
    "children": [
      {
        "id": "e9fe0572417e9879",
        "type": "tabs",
        "children": [
          {
            "id": "b2ce98b54424e7ab",
            "type": "leaf",
            "state": {
              "type": "markdown",
              "state": {
                "file": "HTB Academy/AD Enumeration & Attacks.md",
                "mode": "source",
                "source": false
              },
              "icon": "lucide-file",
              "title": "AD Enumeration & Attacks"
            }
          },
          {
            "id": "0d3ba7e25224702e",
            "type": "leaf",
            "state": {
              "type": "markdown",
              "state": {
                "file": "HTB Academy/File Upload Attacks.md",
                "mode": "source",
                "source": false
              },
              "icon": "lucide-file",
              "title": "File Upload Attacks"
            }
          },
          {
            "id": "9f6ba3b95fe6df6d",
            "type": "leaf",
            "state": {
              "type": "markdown",
              "state": {
                "file": "Prompt Anki.md",
                "mode": "source",
                "source": false
              },
              "icon": "lucide-file",
              "title": "Prompt Anki"
            }
          }
        ],
        "currentTab": 2
      }
    ],
    "direction": "vertical"
  },
  "left": {
    "id": "64195fde1a65bbfe",
    "type": "split",
    "children": [
      {
        "id": "458c5ceffa5b2f32",
        "type": "tabs",
        "children": [
          {
            "id": "998371bfb0c47842",
            "type": "leaf",
            "state": {
              "type": "file-explorer",
              "state": {
                "sortOrder": "alphabetical",
                "autoReveal": true
              },
              "icon": "lucide-folder-closed",
              "title": "Files"
            }
          },
          {
            "id": "b73530377d2e941e",
            "type": "leaf",
            "state": {
              "type": "search",
              "state": {
                "query": "",
                "matchingCase": false,
                "explainSearch": false,
                "collapseAll": false,
                "extraContext": false,
                "sortOrder": "alphabetical"
              },
              "icon": "lucide-search",
              "title": "Search"
            }
          },
          {
            "id": "31e6db53b562b8b7",
            "type": "leaf",
            "state": {
              "type": "bookmarks",
              "state": {},
              "icon": "lucide-bookmark",
              "title": "Bookmarks"
            }
          }
        ]
      }
    ],
    "direction": "horizontal",
    "width": 247.5
  },
  "right": {
    "id": "7ed3b308ddb0d00e",
    "type": "split",
    "children": [
      {
        "id": "199c8d1ae059f9d2",
        "type": "tabs",
        "children": [
          {
            "id": "e9788a5712aab402",
            "type": "leaf",
            "state": {
              "type": "backlink",
              "state": {
                "file": "Linux/Wireshark.md",
                "collapseAll": false,
                "extraContext": true,
                "sortOrder": "alphabetical",
                "showSearch": true,
                "searchQuery": "",
                "backlinkCollapsed": false,
                "unlinkedCollapsed": false
              },
              "icon": "links-coming-in",
              "title": "Backlinks for Wireshark"
            }
          },
          {
            "id": "80f97a3d35bf525d",
            "type": "leaf",
            "state": {
              "type": "outgoing-link",
              "state": {
                "file": "Linux/KVM (virt-manager).md",
                "linksCollapsed": false,
                "unlinkedCollapsed": true
              },
              "icon": "links-going-out",
              "title": "Outgoing links from KVM (virt-manager)"
            }
          },
          {
            "id": "e767e174aa2076eb",
            "type": "leaf",
            "state": {
              "type": "tag",
              "state": {
                "sortOrder": "frequency",
                "useHierarchy": true,
                "showSearch": false,
                "searchQuery": ""
              },
              "icon": "lucide-tags",
              "title": "Tags"
            }
          },
          {
            "id": "b8017e1a9f7dfd55",
            "type": "leaf",
            "state": {
              "type": "outline",
              "state": {
                "file": "Prompt Anki.md",
                "followCursor": true,
                "showSearch": false,
                "searchQuery": ""
              },
              "icon": "lucide-list",
              "title": "Outline of Prompt Anki"
            }
          }
        ],
        "currentTab": 3
      }
    ],
    "direction": "horizontal",
    "width": 200
  },
  "left-ribbon": {
    "hiddenItems": {
      "switcher:Open quick switcher": false,
      "graph:Open graph view": false,
      "canvas:Create new canvas": false,
      "daily-notes:Open today's daily note": false,
      "templates:Insert template": false,
      "command-palette:Open command palette": false,
      "bases:Create new base": false
    }
  },
  "active": "9f6ba3b95fe6df6d",
  "lastOpenFiles": [
    "HTB Academy/AD Enumeration & Attacks.md",
    "Prompt Anki.md",
    "HTB Academy/Windows PrivEsc.md",
    "HTB Academy/File Upload Attacks.md",
    "HTB Academy/Password Attacks.md",
    "HTB Academy/Server-Side Attacks.md",
    "HTB Academy/Pivoting, Tunneling, and Port Forwarding.md",
    "HTB Academy/Attacking Common App.md",
    "HTB Academy/Attacking Common Services.md",
    "Networking Labs/arista - mlag client.md",
    "HTB Academy/SQL Injection Fundamentals.md",
    "HTB Academy/images/Pasted image 20260128063743.png",
    "HTB Academy/images/Pasted image 20260128063706.png",
    "HTB Academy/CrackMapExec (Netexec).md",
    "HTB Academy/File Inclusion.md",
    "Networking Labs/arista - l2evpn vxlan.md",
    "HTB Academy/Footprinting.md",
    "Networking Labs/arista - vxlan HER.md",
    "HTB Academy/Web Attacks.md",
    "HTB Academy/Untitled 1.md",
    "Networking Labs/junos - l2evpn basic.md",
    "consistency-report.md",
    "Networking Labs",
    "HTB Academy/images/Pasted image 20260115114204.png",
    "HTB Academy/images/Pasted image 20260115092113.png",
    "HTB Academy/Command Injection.md",
    "Linux/KVM (virt-manager).md",
    "machine-list-todo.ods",
    "lu413367169e19.tmp",
    "HTB Academy/SQLMap Essentials.md",
    "HTB Academy/images/Pasted image 20260111145954.png",
    "HTB Academy/images/Pasted image 20260111103921.png",
    "HTB Academy/images/Pasted image 20260111103541.png",
    "HTB Academy/images/Pasted image 20260111103105.png",
    "HTB Academy/images/Pasted image 20260111103040.png",
    "HTB Academy/images/Pasted image 20260111102958.png",
    "inlanefreight.com_ips.txt",
    "Machines/{2025-9-5} HTB_Mirai.md",
    "Machines/{2025-8-25} HTB_Nibbles.md",
    "THM Cheat Sheet/images",
    "!! TODO.md",
    "Python",
    "Linux/images",
    "Javascript",
    "Code",
    "HTB Academy/Linux PrivEsc"
  ]
}